{
  "nttId": "36500",
  "board": "B0000207",
  "menuNo": "200691",
  "source": "voice2",
  "view_url": "https://www.fss.or.kr/fss/bbs/B0000207/view.do?nttId=36500&menuNo=200691",
  "title": "수사기관 사칭형(검찰, 경찰 등)(상세) | 그놈 목소리 | 보이스피싱 체험관 | 보이스피싱 사전예방 | 보이스피싱지킴이 | 민원·신고 |",
  "text": "그놈 목소리\n바로 이 목소리\n보이스피싱 사이버체험관\n그놈 목소리\n대출사기형\n수사기관 사칭형(검찰, 경찰 등)\n안전계좌로 돈을 옮기고 동결처리했다.\n작성자\n안태승\n등록일\n2015-10-27\n조회수\n3018\n담당부서\n서민금융지원국\n담당팀\n서민금융총괄팀\n문의\n02-3145-8123\n목록\n이전글\n절대 검찰조사 받는 것 발설하지 마세요\n다음글\n피해자 입증이 되어야 고소고발이 취하된다.",
  "audio": [
    "https://www.fss.or.kr/fss/cmmn/file/fileDown.do?menuNo=200691&atchFileId=8057125e91813747e68d0a9456cd2acb&fileSn=1&bbsId=B0000207",
    "https://www.fss.or.kr/comm/getFile.do?atchFileId=8057125e91813747e68d0a9456cd2acb&fileSn=0",
    "https://www.fss.or.kr/comm/getFile.do?atchFileId=8057125e91813747e68d0a9456cd2acb&fileSn=1"
  ]
}