{
  "nttId": "18303",
  "board": "B0000203",
  "menuNo": "200686",
  "source": "video",
  "view_url": "https://www.fss.or.kr/fss/bbs/B0000203/view.do?nttId=18303&menuNo=200686",
  "title": "바로 이 목소리(상세) | 보이스피싱 체험관 | 보이스피싱 사전예방 | 보이스피싱지킴이 | 민원·신고 |",
  "text": "바로 이 목소리\n바로 이 목소리\n보이스피싱 사이버체험관\n그놈 목소리\n5차례 신고된 남성 전화금융사기범 음성 4\n등록일\n2020-01-06\n조회수\n4680\n영상파일\n5차례 신고된 남성 전화금융사기범 음성 4.mp4\n(파일크기: 27KB)\n바로 이 목소리\n(수차례 신고된 보이스피싱 사기범 음성)\n5차례 신고된 남성 전화금융사기범 음성 4\n금융감독원 / NFS국립과학수사연구원\n첫 번째 신고 목소리\n사기범 : 네. 일단 정확히 저희 검찰에서 연락드린 요점은 본인이 금전적인 대가성을 받고 김용식 일당들에게 통장을 판매한 가해자이신지 그게 아니시면 개인정보 유출로 명의도용을 당하신 피해자분이신지 그 진위 여부를 파악하고자 연락을 드린 겁니다.\n하나은행 금융권이요.\n일단 금융감독원 측에서 저희 쪽으로 전달해온 게 2016년 1월 27일 경기도 광명시 철산동 지점을 통해서 개설이 되었다고 확인이 됩니다.\n네. 본인께서 직접적으로 개설을 하셨죠?\n그쪽에서 개설을 안 하셨다 그 말씀이신가요?\n그럼 본인은 제3자에게 통장 개설을 해서 양도나 혹은 판매하신 적이 없다 그 말씀이신 거죠?\n네. 일단 그러시면 먼저 본인의 통장이 불법적으로 사용이 되었기 때문에 사건 경위에 대해서 간략하게 설명 좀 해드릴게요.\n네. 혹시 그 중고나라 사이트 알고 계시죠?\n네. 일단 그 중고나라 사이트에서 김용식 일당들이 고가의 물건을 저가에 판매한다는 명목하에 등록된 통장을 사용하여 입금을 유도한 뒤 자금만 인출하고 현재 도주 잠적한 상태입니다.\n따라서 물건을 받지 않는 피해자분들이 발생이 되었고, 그 피해자분들이 현재 XXX씨 앞으로 고소, 고발 조치가 취해진 상태이고 피해 금액이 형성되었습니다.\n지금까지 발생된 피해 금액은 대략적으로 2,300만원 정도가 되는데…\n두 번째 신고 목소리\n사기범 : 아시는거에서만 솔직하게 답변만 해주시면 되겠습니다. 아시겠죠?\n네. 일단 추가적인 조사를 위해서 현시점부터 조사 과정은 녹취 상태로 진행할 겁니다.\n이 녹취를 진행하는 이유는 다음 주에 있을 김용식 관련 재판에 XXX씨께서 직접 재판장에 출석하실 건 아니시고 일단 본인을 대신해 피해자 입증을 도와줄 증거자료로 만드는 겁니다.\n일단 녹취되기 전에 제3자의 육성이나 기타 소음이 유입될 시 본인 증거자료의 조작 가능성이 있다…\n세 번째 신고 목소리\n사기범 : 그리고 이 번호로 녹취 상태로도 진행을 해야 되기 때문이죠.\n네. 이해가 되시나요?\n원래 본 사건은 본인뿐만이 아니고 180여명에서 200여명 정도가 연루가 되어있는 금융사기 사건입니다.\n근데 이 200여명 중 가해자보다 피해자가 많기 때문에 1차 피해 혐의점이 없는 분들 한해서 약식 조사를 실시하고 있는 거고요.\n네. 그러면 본인께서는 뭐 공무원 쪽에서 이렇게 근무를 하고 계시는 거 같은데 저희가 뭐 직장 때문에 저희가 약식 조사를 실시하고 있는 겁니다.\n네. 그럼 뭐 김용식이라고 처음 들어보셨어요?\n네. 일단 저희 검찰 측에서 김용식 필두로 인한 금융범죄사기단을 검거한 상태인데 근데 이 검거 현장에서 대량의 신용카드와 대포통장을 압수를 하던 과정에서 XXX씨 명의로 된 농협, 하나은행 통장 두 점이 발견되어서 조사차 연락을 드린 겁니다.\n네 번째 신고 목소리\n사기범 : 피해금은 대략 2,300만원 정도가 되는데 뭐 궁금하시거나 이해가 안 가시는 내용이 있으신가요?\n일단 그래서 금일 안으로 피해자 입증만 받게 되시면 이 고소, 고발조치나 피해 금액은 전부 취하 처리가 될 수 있으니까 너무 걱정 마시고 아시는 내용 그대로 말씀만 해주시면 됩니다.\n본 사건은 본인뿐만이 아니고 180여명에서 200여명 정도가 연루되어 있는 금융사기 사건입니다.\n근데 이 200여명 중 가해자보다 피해자가 많기 때문에 1차 피해 혐의점이 없는 분들 한해서 약식 조사를 실시하고 있는데 뭐 또 궁금하신 거 있으세요?\n네네. 직접적으로 오신다고요? 서울중앙 지방검찰청으로 오셔야 됩니다.\n유선상 약식 조사를 원치 않으시면 금일 안으로 본청에 방문하셔야 되는 거에요.\n다섯 번째 신고 목소리\n사기범 : 네. 서울중앙지검에 이기훈 수사관입니다. 현재 본인과 연루된 개인정보 유출 건 때문에 몇 가지 확인차 연락을 드렸습니다.\n본인 혹시 김용식이라고 들어보신 적 있으신가요?\n네. 처음 들어보셨어요?\n네. 일단 저희 검찰 측에서 김용식 필두로 인한 금융범죄사기단을 검거한 상태인데 근데 이 검거 현장에서 대량의 신용카드와 대포통장을 압수를 하던 과정에서 XXX씨 명의로 된 농협, 하나은행 통장 두 점이 발견되어서 조사차 연락을 드린 겁니다.\n일단 정확히 연락하는 요점은 본인이 금전적인 대가성을 받고 김용식 일당들에게 통장을 판매한 가해자이신지 아니시면 개인정보 유출로 인한 명의도용을 당하신 피해자분이신지 그 진위 여부를 파악하고자 연락을 드린 겁니다.\n네. 그럼 본인께서 이 통장 개설 건에 대해서 뭐 알고 계신 내용이 있으십니까?\n네. 전혀 모르셨나요? 혹시?\n아~ 네네. 일단 사건 경위에 대해서 말씀을 드리자면 중고나라 사이트 알고 계시죠?\n네. 일단 그 중고나라 사이트에서 김용식 일당들이 고가의 물건을 저가에 판매한다는 명목하에 XXX씨 명의로 된 통장을 사용하여 입금을 유도한 뒤 자금만 인출하고 현재 도주 잠적한 상태입니다.\n네. 따라서… 네. 따라서 물건을 받지 못한 피해자분들이 발생이 되었고 그 피해자분들이 현재 본인 앞으로 고소, 고발 조치가 취해진 상태이고 피해 금액이 형성되었습니다.\n피해금은 대략 2,300만원 정도가 되는데 뭐 궁금하시거나 이해가 안 가시는 내용이 있으신가요?\n금감원과 국과수는 보이스피싱 사기범 음성분석을 통해 끝까지 추적합니다.\n더 이상 보이스피싱 전화 NO!\n피해상담 1332\n피해신고 112\n금융감독원 / NFS국립과학수사연구원\n목록\n이전글\n5차례 신고된 남성 전화금융사기범 음성 3\n다음글\n5차례 신고된 남성 전화금융사기범 음성 5",
  "audio": [
    "https://www.fss.or.kr/fss/cmmn/vodApi/apiVodDownload.do?mediaId=a8dd605dd9a242729979c0ee02257719&atchFileId=192094834b88c493e0aeb52b76a4ba46&fileSn=2",
    "https://vod.fss.or.kr/upload/encoding/video/2021/11/a8dd605dd9a242729979c0ee02257719_media_1280x720.mp4",
    "https://https://nvod.fss.or.kr:1935/upload/encoding/video/2021/12/02ad42f788454cc4ad75cbba9c957d3a_media_1280x720.mp4",
    "https://www.fss.or.kr/comm/getFile.do?atchFileId=192094834b88c493e0aeb52b76a4ba46&fileSn=0",
    "https://www.fss.or.kr/comm/getFile.do?atchFileId=192094834b88c493e0aeb52b76a4ba46&fileSn=1"
  ]
}